{
    "results":[
        {
            "gender":"male",
            "name":{
                "title":"Mr",
                "first":"Cristian",
                "last":"Román"
            },
            "location":{
                "street":{
                    "number":4124,
                    "name":"Avenida de Salamanca"
                },
                "city":"Santander",
                "state":"Canarias",
                "country":"Spain",
                "postcode":30775,
                "coordinates":{
                    "latitude":"-34.3416",
                    "longitude":"-132.6330"
                },
                "timezone":{
                    "offset":"-5:00",
                    "description":"Eastern Time (US & Canada), Bogota, Lima"
                }
            },
            "email":"cristian.roman@example.com",
            "login":{
                "uuid":"3c362c23-283a-4d93-afec-fa5f0be35de8",
                "username":"tinyrabbit974",
                "password":"wannabe",
                "salt":"jHmQYMnO",
                "md5":"3ddf432d6e627a76bb4ce91a8eca8550",
                "sha1":"b524ed0a2194da272cdb92a5a6d39db49bb862f7",
                "sha256":"08a24eb25a22c58357c88bea3a863ee7fbb5ba8d3bccbaa623915bb9deab1cae"
            },
            "dob":{
                "date":"1982-03-25T10:46:35.972Z",
                "age":40
            },
            "registered":{
                "date":"2009-01-28T04:55:23.535Z",
                "age":14
            },
            "phone":"907-923-895",
            "cell":"671-950-322",
            "id":{
                "name":"DNI",
                "value":"85887677-U"
            },
            "picture":{
                "large":"https://randomuser.me/api/portraits/men/97.jpg",
                "medium":"https://randomuser.me/api/portraits/med/men/97.jpg",
                "thumbnail":"https://randomuser.me/api/portraits/thumb/men/97.jpg"
            },
            "nat":"ES"
        }
    ],
    "info":{
        "seed":"de7ff4d2922853a1",
        "results":1,
        "page":1,
        "version":"1.4"
    }
}